sco_worker-0.4.0.dist-info/DESCRIPTION.rst
sco_worker-0.4.0.dist-info/METADATA
sco_worker-0.4.0.dist-info/RECORD
sco_worker-0.4.0.dist-info/WHEEL
sco_worker-0.4.0.dist-info/metadata.json
sco_worker-0.4.0.dist-info/top_level.txt
scoworker/__init__.py
scoworker/convert.py
scoworker/cortical.py
scoworker/rabbitmq_worker.py
scoworker/socket_backend.py
scoworker/workflow.py
